{
  "type": "lesson",
  "id": "lesson_3_numbers",
  "chapterId": "ch_4_numbers_time",
  "title": "Упражнение: Время суток",
  "titleTuvan": "Күүседилге: Хүннүң үези",
  "description": "Названия частей суток и базовые вопросы о времени.",
  "skill": "vocabulary",
  "order": 4,
  "isPublished": true,
  "difficulty": 1,
  "estimatedTime": 12,
  "exercises": [
    {
      "type": "choice",
      "question": "Что означает слово 'Эртен'?",
      "options": [
        "Вечер",
        "Утро",
        "Ночь",
        "День"
      ],
      "correct": "Утро",
      "id": "lesson-03-numbers_1",
      "order": 0
    },
    {
      "type": "translate",
      "question": "День",
      "correct": "Хүн",
      "id": "lesson-03-numbers_2",
      "order": 1
    },
    {
      "type": "match",
      "question": "Соотнесите время суток с переводом:",
      "matchPairs": [
        {
          "left": "Эртен",
          "right": "Утро"
        },
        {
          "left": "Кежээ",
          "right": "Вечер"
        },
        {
          "left": "Соңгу",
          "right": "Ночь"
        }
      ],
      "id": "lesson-03-numbers_3",
      "order": 2
    },
    {
      "type": "choice",
      "question": "Как спросить 'Который час?' (дословно: Сколько времени?)",
      "options": [
        "Кажан?",
        "Хире үе?",
        "Кайы хүн?",
        "Хире сен?"
      ],
      "correct": "Хире үе?",
      "id": "lesson-03-numbers_4",
      "order": 3
    }
  ]
}