{
    "type": "lesson",
    "id": "lesson_2_13-shopping",
    "chapterId": "ch_13-shopping",
    "title": "Покупки (урок 2)",
    "titleTuvan": "Садыг (кичээл 2)",
    "description": "Покупка одежды",
    "skill": "shopping",
    "order": 3,
    "isPublished": true,
    "difficulty": 2,
    "estimatedTime": 12,
    "exercises": [
        {
            "id": "ex_shop_2_1",
            "type": "translate",
            "order": 0,
            "question": "Переведи: 'Размер'",
            "correct": "Хемчээл"
        },
        {
            "id": "ex_shop_2_2",
            "type": "choice",
            "order": 1,
            "question": "Что такое 'Доозал'?",
            "options": ["Цена", "Скидка", "Магазин"],
            "correct": "Скидка"
        },
        {
            "id": "ex_shop_2_3",
            "type": "order",
            "order": 2,
            "question": "Составь фразу: 'Купить хлеб' (Нан садып алыр)",
            "orderItems": ["алыр", "Нан", "садып"],
            "correct": ["Нан", "садып", "алыр"]
        },
        {
            "id": "ex_shop_2_4",
            "type": "match",
            "order": 3,
            "question": "Сопоставь",
            "matchPairs": [
                { "left": "Садып алыр", "right": "Купить" },
                { "left": "Доозал", "right": "Скидка" },
                { "left": "Хемчээл", "right": "Размер" }
            ]
        }
    ]
}
