{
    "words": [
        {
            "id": "w_001",
            "wordTuvan": "Экии",
            "wordRussian": "Здравствуйте / Привет",
            "transcription": "[e'ki:]",
            "partOfSpeech": "interjection",
            "difficulty": 1,
            "categories": ["greetings"],
            "exampleSentence": "Экии, мен Айдын мен.",
            "exampleTranslation": "Привет, я Айдын."
        },
        {
            "id": "w_002",
            "wordTuvan": "Экии-сиңнер",
            "wordRussian": "Здравствуйте (множественное число)",
            "transcription": "[e'ki: siŋ'ner]",
            "partOfSpeech": "interjection",
            "difficulty": 1,
            "categories": ["greetings"],
            "exampleSentence": "Экии-сиңнер, силер кижилер бе?",
            "exampleTranslation": "Здравствуйте, вы люди?"
        },
        {
            "id": "w_003",
            "wordTuvan": "Байырлыы",
            "wordRussian": "Спасибо",
            "transcription": "[ba'jyrly:]",
            "partOfSpeech": "interjection",
            "difficulty": 1,
            "categories": ["greetings"],
            "exampleSentence": "Эки, байырлыы.",
            "exampleTranslation": "Хорошо, спасибо."
        },
        {
            "id": "w_004",
            "wordTuvan": "Кудум",
            "wordRussian": "Извини / Прости",
            "transcription": "[ku'dum]",
            "partOfSpeech": "interjection",
            "difficulty": 1,
            "categories": ["greetings"],
            "exampleSentence": "Кудум, мен медербес.",
            "exampleTranslation": "Извини, я не знаю."
        },
        {
            "id": "w_005",
            "wordTuvan": "Бараалдажыр",
            "wordRussian": "До свидания",
            "transcription": "[ba'ra:lady:r]",
            "partOfSpeech": "interjection",
            "difficulty": 1,
            "categories": ["greetings"],
            "exampleSentence": "Бараалдажыр, мен баар мен.",
            "exampleTranslation": "До свидания, я ушел."
        },
        {
            "id": "w_006",
            "wordTuvan": "Кандыг-дир сен?",
            "wordRussian": "Как дела? (досл. Какой ты есть?)",
            "transcription": "[kan'dyg dir sen]",
            "partOfSpeech": "phrase",
            "difficulty": 1,
            "categories": ["greetings"],
            "exampleSentence": "Кандыг-дир сен?",
            "exampleTranslation": "Как дела?"
        },
        {
            "id": "w_007",
            "wordTuvan": "Эртенги экии",
            "wordRussian": "Доброе утро",
            "transcription": "[er'tengi e'ki:]",
            "partOfSpeech": "phrase",
            "difficulty": 1,
            "categories": ["greetings", "time"],
            "exampleSentence": "Эртенги экии!",
            "exampleTranslation": "Доброе утро!"
        },
        {
            "id": "w_008",
            "wordTuvan": "Хүннүң экии",
            "wordRussian": "Добрый день",
            "transcription": "[hyn'nyŋ e'ki:]",
            "partOfSpeech": "phrase",
            "difficulty": 1,
            "categories": ["greetings", "time"],
            "exampleSentence": "Хүннүң экии!",
            "exampleTranslation": "Добрый день!"
        },
        {
            "id": "w_009",
            "wordTuvan": "Кежээлиги экии",
            "wordRussian": "Добрый вечер",
            "transcription": "[keże:'ligi e'ki:]",
            "partOfSpeech": "phrase",
            "difficulty": 1,
            "categories": ["greetings", "time"],
            "exampleSentence": "Кежээлиги экии!",
            "exampleTranslation": "Добрый вечер!"
        },
        {
            "id": "w_010",
            "wordTuvan": "Соңгу экии",
            "wordRussian": "Спокойной ночи",
            "transcription": "[soŋ'gu e'ki:]",
            "partOfSpeech": "phrase",
            "difficulty": 1,
            "categories": ["greetings", "time"],
            "exampleSentence": "Соңгу экии.",
            "exampleTranslation": "Спокойной ночи."
        },
        {
            "id": "w_011",
            "wordTuvan": "Мээң адым",
            "wordRussian": "Меня зовут (Мое имя)",
            "transcription": "[me:ŋ a'dym]",
            "partOfSpeech": "phrase",
            "difficulty": 1,
            "categories": ["greetings"],
            "exampleSentence": "Мээң адым Анна.",
            "exampleTranslation": "Меня зовут Анна."
        },
        {
            "id": "w_012",
            "wordTuvan": "Ийе",
            "wordRussian": "Да",
            "transcription": "[i:'je]",
            "partOfSpeech": "other",
            "difficulty": 1,
            "categories": ["basics"],
            "exampleSentence": "Ийе, мен.",
            "exampleTranslation": "Да, я."
        },
        {
            "id": "w_013",
            "wordTuvan": "Чок",
            "wordRussian": "Нет",
            "transcription": "[chok]",
            "partOfSpeech": "other",
            "difficulty": 1,
            "categories": ["basics"],
            "exampleSentence": "Чок, мен эвес.",
            "exampleTranslation": "Нет, не я."
        },
        {
            "id": "w_014",
            "wordTuvan": "Бо",
            "wordRussian": "Это",
            "transcription": "[bo]",
            "partOfSpeech": "pronoun",
            "difficulty": 1,
            "categories": ["basics"],
            "exampleSentence": "Бо кым бо?",
            "exampleTranslation": "Это кто?"
        },
        {
            "id": "w_015",
            "wordTuvan": "Кижи",
            "wordRussian": "Человек",
            "transcription": "[ki'zhi]",
            "partOfSpeech": "noun",
            "difficulty": 1,
            "categories": ["description"],
            "exampleSentence": "Ол кижи-дыр.",
            "exampleTranslation": "Он человек."
        },
        {
            "id": "w_016",
            "wordTuvan": "Эр кижи",
            "wordRussian": "Мужчина",
            "transcription": "[er ki'zhi]",
            "partOfSpeech": "noun",
            "difficulty": 1,
            "categories": ["description"],
            "exampleSentence": "Бо эр кижи.",
            "exampleTranslation": "Это мужчина."
        },
        {
            "id": "w_017",
            "wordTuvan": "Кыс кижи",
            "wordRussian": "Женщина",
            "transcription": "[kys ki'zhi]",
            "partOfSpeech": "noun",
            "difficulty": 1,
            "categories": ["description"],
            "exampleSentence": "Ол кыс кижи-дыр.",
            "exampleTranslation": "Она женщина."
        },
        {
            "id": "w_018",
            "wordTuvan": "Оол",
            "wordRussian": "Мальчик / Сын",
            "transcription": "[o:l]",
            "partOfSpeech": "noun",
            "difficulty": 1,
            "categories": ["family", "description"],
            "exampleSentence": "Мен оол мен.",
            "exampleTranslation": "Я мальчик."
        },
        {
            "id": "w_019",
            "wordTuvan": "Кыс",
            "wordRussian": "Девочка / Дочь",
            "transcription": "[kys]",
            "partOfSpeech": "noun",
            "difficulty": 1,
            "categories": ["family", "description"],
            "exampleSentence": "Ол кыс-тыр.",
            "exampleTranslation": "Она девочка."
        },
        {
            "id": "w_020",
            "wordTuvan": "Ача",
            "wordRussian": "Ребенок",
            "transcription": "[a'cha]",
            "partOfSpeech": "noun",
            "difficulty": 1,
            "categories": ["family"],
            "exampleSentence": "Бис ачалар эвес бис.",
            "exampleTranslation": "Мы не дети."
        },
        {
            "id": "w_021",
            "wordTuvan": "Кым",
            "wordRussian": "Кто",
            "transcription": "[kym]",
            "partOfSpeech": "pronoun",
            "difficulty": 1,
            "categories": ["questions"],
            "exampleSentence": "Кым бо?",
            "exampleTranslation": "Кто это?"
        },
        {
            "id": "w_022",
            "wordTuvan": "Чүү",
            "wordRussian": "Что",
            "transcription": "[chüü]",
            "partOfSpeech": "pronoun",
            "difficulty": 1,
            "categories": ["questions"],
            "exampleSentence": "Чүү бо?",
            "exampleTranslation": "Что это?"
        },
        {
            "id": "w_023",
            "wordTuvan": "Кайыан",
            "wordRussian": "Где",
            "transcription": "[ka'y'an]",
            "partOfSpeech": "pronoun",
            "difficulty": 1,
            "categories": ["questions"],
            "exampleSentence": "Кайыан сен?",
            "exampleTranslation": "Ты где?"
        },
        {
            "id": "w_024",
            "wordTuvan": "Кудаа",
            "wordRussian": "Куда",
            "transcription": "[ku'da:]",
            "partOfSpeech": "pronoun",
            "difficulty": 2,
            "categories": ["questions"],
            "exampleSentence": "Кудаа сен чор сен?",
            "exampleTranslation": "Куда ты едешь?"
        },
        {
            "id": "w_025",
            "wordTuvan": "Кажан",
            "wordRussian": "Когда",
            "transcription": "[ka'zhan]",
            "partOfSpeech": "pronoun",
            "difficulty": 2,
            "categories": ["questions"],
            "exampleSentence": "Кажан чор сен?",
            "exampleTranslation": "Когда ты ушел?"
        },
        {
            "id": "w_026",
            "wordTuvan": "Чүге",
            "wordRussian": "Почему / Зачем",
            "transcription": "[chü'ge]",
            "partOfSpeech": "pronoun",
            "difficulty": 2,
            "categories": ["questions"],
            "exampleSentence": "Чүге келдинг?",
            "exampleTranslation": "Почему ты пришел?"
        },
        {
            "id": "w_027",
            "wordTuvan": "Канчап",
            "wordRussian": "Как",
            "transcription": "[kan'chap]",
            "partOfSpeech": "pronoun",
            "difficulty": 2,
            "categories": ["questions"],
            "exampleSentence": "Канчап-дыр сен?",
            "exampleTranslation": "Как ты?"
        },
        {
            "id": "w_028",
            "wordTuvan": "Хире",
            "wordRussian": "Сколько",
            "transcription": ["hi're"],
            "partOfSpeech": "pronoun",
            "difficulty": 2,
            "categories": ["questions"],
            "exampleSentence": "Үнези хире?",
            "exampleTranslation": "Сколько стоит?"
        },
        {
            "id": "w_029",
            "wordTuvan": "Мээң",
            "wordRussian": "Мой",
            "transcription": "[me:ŋ]",
            "partOfSpeech": "pronoun",
            "difficulty": 1,
            "categories": ["family", "basics"],
            "exampleSentence": "Мээң адам.",
            "exampleTranslation": "Мой папа."
        },
        {
            "id": "w_030",
            "wordTuvan": "Сээң",
            "wordRussian": "Твой",
            "transcription": "[se:ŋ]",
            "partOfSpeech": "pronoun",
            "difficulty": 1,
            "categories": ["family", "basics"],
            "exampleSentence": "Сээң адаң.",
            "exampleTranslation": "Твой папа."
        },
        {
            "id": "w_031",
            "wordTuvan": "Ооң",
            "wordRussian": "Его / Ее",
            "transcription": "[o:ŋ]",
            "partOfSpeech": "pronoun",
            "difficulty": 2,
            "categories": ["family", "basics"],
            "exampleSentence": "Ооң авазы.",
            "exampleTranslation": "Его мама."
        },
        {
            "id": "w_032",
            "wordTuvan": "Ава",
            "wordRussian": "Мама",
            "transcription": "[a'va]",
            "partOfSpeech": "noun",
            "difficulty": 1,
            "categories": ["family"],
            "exampleSentence": "Мээң авам.",
            "exampleTranslation": "Моя мама."
        },
        {
            "id": "w_033",
            "wordTuvan": "Ада",
            "wordRussian": "Папа",
            "transcription": "[a'da]",
            "partOfSpeech": "noun",
            "difficulty": 1,
            "categories": ["family"],
            "exampleSentence": "Мээң адам.",
            "exampleTranslation": "Мой папа."
        },
        {
            "id": "w_034",
            "wordTuvan": "Акы",
            "wordRussian": "Старший брат",
            "transcription": "[a'ky]",
            "partOfSpeech": "noun",
            "difficulty": 1,
            "categories": ["family"],
            "exampleSentence": "Мээң акым.",
            "exampleTranslation": "Мой брат."
        },
        {
            "id": "w_035",
            "wordTuvan": "Угбай",
            "wordRussian": "Старшая сестра",
            "transcription": "[ug'bay]",
            "partOfSpeech": "noun",
            "difficulty": 2,
            "categories": ["family"],
            "exampleSentence": "Сээң угбаң.",
            "exampleTranslation": "Твоя сестра."
        },
        {
            "id": "w_036",
            "wordTuvan": "Ийи",
            "wordRussian": "Младший брат/сестра",
            "transcription": "[i:'ji]",
            "partOfSpeech": "noun",
            "difficulty": 2,
            "categories": ["family"],
            "exampleSentence": "Мээң ийим.",
            "exampleTranslation": "Моя младшая сестра."
        },
        {
            "id": "w_037",
            "wordTuvan": "Кырган-ава",
            "wordRussian": "Бабушка",
            "transcription": "[kyr'gan a'va]",
            "partOfSpeech": "noun",
            "difficulty": 1,
            "categories": ["family"],
            "exampleSentence": "Мээң кырган-авам.",
            "exampleTranslation": "Моя бабушка."
        },
        {
            "id": "w_038",
            "wordTuvan": "Кырган-ада",
            "wordRussian": "Дедушка",
            "transcription": "[kyr'gan a'da]",
            "partOfSpeech": "noun",
            "difficulty": 1,
            "categories": ["family"],
            "exampleSentence": "Мээң кырган-адам.",
            "exampleTranslation": "Мой дедушка."
        },
        {
            "id": "w_039",
            "wordTuvan": "Өг-бүле",
            "wordRussian": "Семья",
            "transcription": "[ög bü'le]",
            "partOfSpeech": "noun",
            "difficulty": 2,
            "categories": ["family"],
            "exampleSentence": "Мээң өг-бүлем.",
            "exampleTranslation": "Моя семья."
        },
        {
            "id": "w_040",
            "wordTuvan": "Назын",
            "wordRussian": "Возраст",
            "transcription": "[na'zyn]",
            "partOfSpeech": "noun",
            "difficulty": 3,
            "categories": ["family"],
            "exampleSentence": "Сээң назың хире?",
            "exampleTranslation": "Сколько тебе лет?"
        },
        {
            "id": "w_041",
            "wordTuvan": "Нан",
            "wordRussian": "Хлеб",
            "transcription": "[nan]",
            "partOfSpeech": "noun",
            "difficulty": 1,
            "categories": ["food"],
            "exampleSentence": "Мен нан чиир мен.",
            "exampleTranslation": "Я буду есть хлеб."
        },
        {
            "id": "w_042",
            "wordTuvan": "Эт",
            "wordRussian": "Мясо",
            "transcription": "[et]",
            "partOfSpeech": "noun",
            "difficulty": 1,
            "categories": ["food"],
            "exampleSentence": "Эт чиир.",
            "exampleTranslation": "Есть мясо."
        },
        {
            "id": "w_043",
            "wordTuvan": "Суг",
            "wordRussian": "Вода",
            "transcription": "[sug]",
            "partOfSpeech": "noun",
            "difficulty": 1,
            "categories": ["food"],
            "exampleSentence": "Суг ижер.",
            "exampleTranslation": "Пить воду."
        },
        {
            "id": "w_044",
            "wordTuvan": "Чай",
            "wordRussian": "Чай",
            "transcription": "[chay]",
            "partOfSpeech": "noun",
            "difficulty": 1,
            "categories": ["food"],
            "exampleSentence": "Чай ижер.",
            "exampleTranslation": "Пить чай."
        },
        {
            "id": "w_045",
            "wordTuvan": "Сүт",
            "wordRussian": "Молоко",
            "transcription": "[süt]",
            "partOfSpeech": "noun",
            "difficulty": 1,
            "categories": ["food"],
            "exampleSentence": "Сүт ижер.",
            "exampleTranslation": "Пить молоко."
        },
        {
            "id": "w_046",
            "wordTuvan": "Дус",
            "wordRussian": "Соль",
            "transcription": "[dus]",
            "partOfSpeech": "noun",
            "difficulty": 2,
            "categories": ["food"],
            "exampleSentence": "Дус бар бе?",
            "exampleTranslation": "Есть соль?"
        },
        {
            "id": "w_047",
            "wordTuvan": "Чигир",
            "wordRussian": "Сахар",
            "transcription": "[chi'gir]",
            "partOfSpeech": "noun",
            "difficulty": 2,
            "categories": ["food"],
            "exampleSentence": "Чигир алыр.",
            "exampleTranslation": "Купить сахар."
        },
        {
            "id": "w_048",
            "wordTuvan": "Далган",
            "wordRussian": "Поджаренная мука",
            "transcription": "[dal'gan]",
            "partOfSpeech": "noun",
            "difficulty": 3,
            "categories": ["food"],
            "exampleSentence": "Далган кылыр.",
            "exampleTranslation": "Готовить далган."
        },
        {
            "id": "w_049",
            "wordTuvan": "Боова",
            "wordRussian": "Жареные лепешки",
            "transcription": "[bo:'va]",
            "partOfSpeech": "noun",
            "difficulty": 3,
            "categories": ["food"],
            "exampleSentence": "Боова чиир.",
            "exampleTranslation": "Есть боова."
        },
        {
            "id": "w_050",
            "wordTuvan": "Тараа",
            "wordRussian": "Пшено / Каша",
            "transcription": "[ta'ra:]",
            "partOfSpeech": "noun",
            "difficulty": 3,
            "categories": ["food"],
            "exampleSentence": "Тараа чиир.",
            "exampleTranslation": "Есть кашу."
        },
        {
            "id": "w_051",
            "wordTuvan": "Эртенги чем",
            "wordRussian": "Завтрак",
            "transcription": "[er'tengi chem]",
            "partOfSpeech": "noun",
            "difficulty": 2,
            "categories": ["food", "daily_routine"],
            "exampleSentence": "Эртенги чем чиир.",
            "exampleTranslation": "Завтракать."
        },
        {
            "id": "w_052",
            "wordTuvan": "Хүн ортузунда чем",
            "wordRussian": "Обед",
            "transcription": "[hyn or'tuzunda chem]",
            "partOfSpeech": "noun",
            "difficulty": 3,
            "categories": ["food", "daily_routine"],
            "exampleSentence": "Хүн ортузунда чем чиип тур мен.",
            "exampleTranslation": "Я обедаю."
        },
        {
            "id": "w_053",
            "wordTuvan": "Кежээки чем",
            "wordRussian": "Ужин",
            "transcription": "[keże:'ki chem]",
            "partOfSpeech": "noun",
            "difficulty": 3,
            "categories": ["food", "daily_routine"],
            "exampleSentence": "Кежээки чем чиир.",
            "exampleTranslation": "Ужинать."
        },
        {
            "id": "w_054",
            "wordTuvan": "Чиир",
            "wordRussian": "Есть, кушать",
            "transcription": "[chiir]",
            "partOfSpeech": "verb",
            "difficulty": 1,
            "categories": ["food"],
            "exampleSentence": "Мен нан чиир мен.",
            "exampleTranslation": "Я буду есть хлеб."
        },
        {
            "id": "w_055",
            "wordTuvan": "Ижер",
            "wordRussian": "Пить",
            "transcription": "[i'zher]",
            "partOfSpeech": "verb",
            "difficulty": 1,
            "categories": ["food"],
            "exampleSentence": "Мен чай ижер мен.",
            "exampleTranslation": "Я буду пить чай."
        },
        {
            "id": "w_056",
            "wordTuvan": "Бир",
            "wordRussian": "Один / 1",
            "transcription": "[bir]",
            "partOfSpeech": "numeral",
            "difficulty": 1,
            "categories": ["numbers"],
            "exampleSentence": "Бир билет.",
            "exampleTranslation": "Один билет."
        },
        {
            "id": "w_057",
            "wordTuvan": "Ийи",
            "wordRussian": "Два / 2",
            "transcription": "[i:'ji]",
            "partOfSpeech": "numeral",
            "difficulty": 1,
            "categories": ["numbers"],
            "exampleSentence": "Ийи кижи.",
            "exampleTranslation": "Два человека."
        },
        {
            "id": "w_058",
            "wordTuvan": "Үш",
            "wordRussian": "Три / 3",
            "transcription": "[ysh]",
            "partOfSpeech": "numeral",
            "difficulty": 1,
            "categories": ["numbers"],
            "exampleSentence": "Үш нан.",
            "exampleTranslation": "Три хлеба."
        },
        {
            "id": "w_059",
            "wordTuvan": "Дөрт",
            "wordRussian": "Четыре / 4",
            "transcription": "[dört]",
            "partOfSpeech": "numeral",
            "difficulty": 1,
            "categories": ["numbers"],
            "exampleSentence": "Дөрт аяк.",
            "exampleTranslation": "Четыре чашки."
        },
        {
            "id": "w_060",
            "wordTuvan": "Беш",
            "wordRussian": "Пять / 5",
            "transcription": "[besh]",
            "partOfSpeech": "numeral",
            "difficulty": 1,
            "categories": ["numbers"],
            "exampleSentence": "Беш ыт.",
            "exampleTranslation": "Пять собак."
        },
        {
            "id": "w_061",
            "wordTuvan": "Алды",
            "wordRussian": "Шесть / 6",
            "transcription": "[al'dy]",
            "partOfSpeech": "numeral",
            "difficulty": 2,
            "categories": ["numbers"],
            "exampleSentence": "Алды хой.",
            "exampleTranslation": "Шесть овец."
        },
        {
            "id": "w_062",
            "wordTuvan": "Чеди",
            "wordRussian": "Семь / 7",
            "transcription": ["che'di"],
            "partOfSpeech": "numeral",
            "difficulty": 2,
            "categories": ["numbers"],
            "exampleSentence": "Чеди инек.",
            "exampleTranslation": "Семь коров."
        },
        {
            "id": "w_063",
            "wordTuvan": "Сегис",
            "wordRussian": "Восемь / 8",
            "transcription": "[se'gis]",
            "partOfSpeech": "numeral",
            "difficulty": 2,
            "categories": ["numbers"],
            "exampleSentence": "Сегис аът.",
            "exampleTranslation": "Восемь лошадей."
        },
        {
            "id": "w_064",
            "wordTuvan": "Тос",
            "wordRussian": "Девять / 9",
            "transcription": "[tos]",
            "partOfSpeech": "numeral",
            "difficulty": 2,
            "categories": ["numbers"],
            "exampleSentence": "Тос эшки.",
            "exampleTranslation": "Девять коз."
        },
        {
            "id": "w_065",
            "wordTuvan": "Он",
            "wordRussian": "Десять / 10",
            "transcription": "[on]",
            "partOfSpeech": "numeral",
            "difficulty": 1,
            "categories": ["numbers"],
            "exampleSentence": "Он кижи.",
            "exampleTranslation": "Десять человек."
        },
        {
            "id": "w_066",
            "wordTuvan": "Чиүй",
            "wordRussian": "Двадцать / 20",
            "transcription": "[chi'üy]",
            "partOfSpeech": "numeral",
            "difficulty": 3,
            "categories": ["numbers"],
            "exampleSentence": "Чиүй ачалар.",
            "exampleTranslation": "Двадцать детей."
        },
        {
            "id": "w_067",
            "wordTuvan": "Ак",
            "wordRussian": "Белый",
            "transcription": "[ak]",
            "partOfSpeech": "adjective",
            "difficulty": 1,
            "categories": ["colors"],
            "exampleSentence": "Ак нан.",
            "exampleTranslation": "Белый хлеб."
        },
        {
            "id": "w_068",
            "wordTuvan": "Кара",
            "wordRussian": "Черный",
            "transcription": "[ka'ra]",
            "partOfSpeech": "adjective",
            "difficulty": 1,
            "categories": ["colors"],
            "exampleSentence": "Кара ыт.",
            "exampleTranslation": "Черная собака."
        },
        {
            "id": "w_069",
            "wordTuvan": "Кызыл",
            "wordRussian": "Красный",
            "transcription": "[ky'zyl]",
            "partOfSpeech": "adjective",
            "difficulty": 1,
            "categories": ["colors"],
            "exampleSentence": "Кызыл эт.",
            "exampleTranslation": "Красное мясо."
        },
        {
            "id": "w_070",
            "wordTuvan": "Ногаан",
            "wordRussian": "Зеленый",
            "transcription": "[no'ga:n]",
            "partOfSpeech": "adjective",
            "difficulty": 1,
            "categories": ["colors"],
            "exampleSentence": "Ногаан от.",
            "exampleTranslation": "Зеленая трава."
        },
        {
            "id": "w_071",
            "wordTuvan": "Көк",
            "wordRussian": "Синий / Голубой",
            "transcription": "[kök]",
            "partOfSpeech": "adjective",
            "difficulty": 1,
            "categories": ["colors"],
            "exampleSentence": "Көк аяк.",
            "exampleTranslation": "Синяя чашка."
        },
        {
            "id": "w_072",
            "wordTuvan": "Сарыг",
            "wordRussian": "Желтый",
            "transcription": "[sa'ryg]",
            "partOfSpeech": "adjective",
            "difficulty": 2,
            "categories": ["colors"],
            "exampleSentence": "Сарыг чай.",
            "exampleTranslation": "Желтый чай."
        },
        {
            "id": "w_073",
            "wordTuvan": "Күрең",
            "wordRussian": "Коричневый",
            "transcription": "[kü'reŋ]",
            "partOfSpeech": "adjective",
            "difficulty": 3,
            "categories": ["colors"],
            "exampleSentence": "Күрең бажың.",
            "exampleTranslation": "Коричневый дом."
        },
        {
            "id": "w_074",
            "wordTuvan": "Бора",
            "wordRussian": "Серый",
            "transcription": "[bo'ra]",
            "partOfSpeech": "adjective",
            "difficulty": 3,
            "categories": ["colors"],
            "exampleSentence": "Бора инек.",
            "exampleTranslation": "Серая корова."
        },
        {
            "id": "w_075",
            "wordTuvan": "Улуг",
            "wordRussian": "Большой",
            "transcription": "[u'lug]",
            "partOfSpeech": "adjective",
            "difficulty": 1,
            "categories": ["description"],
            "exampleSentence": "Улуг бажың.",
            "exampleTranslation": "Большой дом."
        },
        {
            "id": "w_076",
            "wordTuvan": "Биче",
            "wordRussian": "Маленький",
            "transcription": ["bi'che"],
            "partOfSpeech": "adjective",
            "difficulty": 1,
            "categories": ["description"],
            "exampleSentence": "Биче аяк.",
            "exampleTranslation": "Маленькая чашка."
        },
        {
            "id": "w_077",
            "wordTuvan": "Чараш",
            "wordRussian": "Красивый",
            "transcription": "[cha'rash]",
            "partOfSpeech": "adjective",
            "difficulty": 1,
            "categories": ["description"],
            "exampleSentence": "Чараш кижи.",
            "exampleTranslation": "Красивый человек."
        },
        {
            "id": "w_078",
            "wordTuvan": "Кырган",
            "wordRussian": "Старый",
            "transcription": "[kyr'gan]",
            "partOfSpeech": "adjective",
            "difficulty": 2,
            "categories": ["description"],
            "exampleSentence": "Кырган кижи.",
            "exampleTranslation": "Старый человек."
        },
        {
            "id": "w_079",
            "wordTuvan": "Аныяк",
            "wordRussian": "Молодой",
            "transcription": "[a'nyak]",
            "partOfSpeech": "adjective",
            "difficulty": 2,
            "categories": ["description"],
            "exampleSentence": "Аныяк эр кижи.",
            "exampleTranslation": "Молодой мужчина."
        },
        {
            "id": "w_080",
            "wordTuvan": "Өр",
            "wordRussian": "Высокий",
            "transcription": "[ör]",
            "partOfSpeech": "adjective",
            "difficulty": 2,
            "categories": ["description"],
            "exampleSentence": "Өр оол.",
            "exampleTranslation": "Высокий мальчик."
        },
        {
            "id": "w_081",
            "wordTuvan": "Ээжик",
            "wordRussian": "Низкий",
            "transcription": "[e:'zhik]",
            "partOfSpeech": "adjective",
            "difficulty": 3,
            "categories": ["description"],
            "exampleSentence": "Ээжик кыс.",
            "exampleTranslation": "Низкая девочка."
        },
        {
            "id": "w_082",
            "wordTuvan": "Дөглүг",
            "wordRussian": "Круглый",
            "transcription": "[dög'lyg]",
            "partOfSpeech": "adjective",
            "difficulty": 4,
            "categories": ["description"],
            "exampleSentence": "Дөглүг аяк.",
            "exampleTranslation": "Круглая чашка."
        },
        {
            "id": "w_083",
            "wordTuvan": "Чаа",
            "wordRussian": "Новый",
            "transcription": "[cha:]",
            "partOfSpeech": "adjective",
            "difficulty": 2,
            "categories": ["description"],
            "exampleSentence": "Чаа стол.",
            "exampleTranslation": "Новый стол."
        },
        {
            "id": "w_084",
            "wordTuvan": "Эң",
            "wordRussian": "Очень",
            "transcription": "[eŋ]",
            "partOfSpeech": "adverb",
            "difficulty": 3,
            "categories": ["description"],
            "exampleSentence": "Эң чараш.",
            "exampleTranslation": "Очень красивый."
        },
        {
            "id": "w_085",
            "wordTuvan": "Малгай",
            "wordRussian": "Шапка",
            "transcription": "[mal'gay]",
            "partOfSpeech": "noun",
            "difficulty": 2,
            "categories": ["clothing"],
            "exampleSentence": "Кара малгай.",
            "exampleTranslation": "Черная шапка."
        },
        {
            "id": "w_086",
            "wordTuvan": "Хөрек",
            "wordRussian": "Рубашка",
            "transcription": "[hö'rek]",
            "partOfSpeech": "noun",
            "difficulty": 2,
            "categories": ["clothing"],
            "exampleSentence": "Кызыл хөрек.",
            "exampleTranslation": "Красная рубашка."
        },
        {
            "id": "w_087",
            "wordTuvan": "Шалбар",
            "wordRussian": "Штаны",
            "transcription": "[shal'bar]",
            "partOfSpeech": "noun",
            "difficulty": 2,
            "categories": ["clothing"],
            "exampleSentence": "Биче шалбар.",
            "exampleTranslation": "Маленькие штаны."
        },
        {
            "id": "w_088",
            "wordTuvan": "Тон",
            "wordRussian": "Шуба",
            "transcription": "[ton]",
            "partOfSpeech": "noun",
            "difficulty": 2,
            "categories": ["clothing"],
            "exampleSentence": "Улуг тон.",
            "exampleTranslation": "Большая шуба."
        },
        {
            "id": "w_089",
            "wordTuvan": "Идик",
            "wordRussian": "Обувь, сапоги",
            "transcription": "[i'dik]",
            "partOfSpeech": "noun",
            "difficulty": 2,
            "categories": ["clothing"],
            "exampleSentence": "Чаа идик.",
            "exampleTranslation": "Новая обувь."
        },
        {
            "id": "w_090",
            "wordTuvan": "Ыт",
            "wordRussian": "Собака",
            "transcription": "[yt]",
            "partOfSpeech": "noun",
            "difficulty": 1,
            "categories": ["animals"],
            "exampleSentence": "Кара ыт.",
            "exampleTranslation": "Черная собака."
        },
        {
            "id": "w_091",
            "wordTuvan": "Кош",
            "wordRussian": "Кошка",
            "transcription": "[kosh]",
            "partOfSpeech": "noun",
            "difficulty": 1,
            "categories": ["animals"],
            "exampleSentence": "Ак кош.",
            "exampleTranslation": "Белая кошка."
        },
        {
            "id": "w_092",
            "wordTuvan": "Аът",
            "wordRussian": "Лошадь",
            "transcription": "[a't]",
            "partOfSpeech": "noun",
            "difficulty": 1,
            "categories": ["animals"],
            "exampleSentence": "Улуг аът.",
            "exampleTranslation": "Большая лошадь."
        },
        {
            "id": "w_093",
            "wordTuvan": "Инек",
            "wordRussian": "Корова",
            "transcription": "[i'nek]",
            "partOfSpeech": "noun",
            "difficulty": 1,
            "categories": ["animals"],
            "exampleSentence": "Бора инек.",
            "exampleTranslation": "Серая корова."
        },
        {
            "id": "w_094",
            "wordTuvan": "Хой",
            "wordRussian": "Овца",
            "transcription": "[hoy]",
            "partOfSpeech": "noun",
            "difficulty": 2,
            "categories": ["animals"],
            "exampleSentence": "Ак хой.",
            "exampleTranslation": "Белая овца."
        },
        {
            "id": "w_095",
            "wordTuvan": "Эшки",
            "wordRussian": "Коза",
            "transcription": "[esh'ki]",
            "partOfSpeech": "noun",
            "difficulty": 2,
            "categories": ["animals"],
            "exampleSentence": "Кара эшки.",
            "exampleTranslation": "Черная коза."
        },
        {
            "id": "w_096",
            "wordTuvan": "Адыг",
            "wordRussian": "Медведь",
            "transcription": "[a'dyg]",
            "partOfSpeech": "noun",
            "difficulty": 2,
            "categories": ["animals"],
            "exampleSentence": "Улуг адыг.",
            "exampleTranslation": "Большой медведь."
        },
        {
            "id": "w_097",
            "wordTuvan": "Бөрү",
            "wordRussian": "Волк",
            "transcription": "[bö'rü]",
            "partOfSpeech": "noun",
            "difficulty": 2,
            "categories": ["animals"],
            "exampleSentence": "Кара бөрү.",
            "exampleTranslation": "Черный волк."
        },
        {
            "id": "w_098",
            "wordTuvan": "Тулгу",
            "wordRussian": "Лиса",
            "transcription": "[tul'gu]",
            "partOfSpeech": "noun",
            "difficulty": 3,
            "categories": ["animals"],
            "exampleSentence": "Кызыл тулгу.",
            "exampleTranslation": "Красная лиса."
        },
        {
            "id": "w_099",
            "wordTuvan": "Бугу",
            "wordRussian": "Олень",
            "transcription": "[bu'gu]",
            "partOfSpeech": "noun",
            "difficulty": 3,
            "categories": ["animals"],
            "exampleSentence": "Биче бугу.",
            "exampleTranslation": "Маленький олень."
        },
        {
            "id": "w_100",
            "wordTuvan": "Куш",
            "wordRussian": "Птица",
            "transcription": "[kush]",
            "partOfSpeech": "noun",
            "difficulty": 2,
            "categories": ["animals"],
            "exampleSentence": "Куш чүү бо?",
            "exampleTranslation": "Что это за птица?"
        },
        {
            "id": "w_101",
            "wordTuvan": "Аң",
            "wordRussian": "Зверь (дикое животное)",
            "transcription": "[aŋ]",
            "partOfSpeech": "noun",
            "difficulty": 3,
            "categories": ["animals"],
            "exampleSentence": "Аңнар.",
            "exampleTranslation": "Дикие животные."
        },
        {
            "id": "w_102",
            "wordTuvan": "Мал",
            "wordRussian": "Скот (домашние животные)",
            "transcription": "[mal]",
            "partOfSpeech": "noun",
            "difficulty": 3,
            "categories": ["animals"],
            "exampleSentence": "Малдар.",
            "exampleTranslation": "Домашние животные."
        },
        {
            "id": "w_103",
            "wordTuvan": "Бажың",
            "wordRussian": "Дом",
            "transcription": "[ba'zhıŋ]",
            "partOfSpeech": "noun",
            "difficulty": 1,
            "categories": ["house"],
            "exampleSentence": "Мээң бажыңым.",
            "exampleTranslation": "Мой дом."
        },
        {
            "id": "w_104",
            "wordTuvan": "Өг",
            "wordRussian": "Юрта",
            "transcription": "[ög]",
            "partOfSpeech": "noun",
            "difficulty": 2,
            "categories": ["house"],
            "exampleSentence": "Бо өг.",
            "exampleTranslation": "Это юрта."
        },
        {
            "id": "w_105",
            "wordTuvan": "Өрээл",
            "wordRussian": "Комната",
            "transcription": "[ö're:l]",
            "partOfSpeech": "noun",
            "difficulty": 2,
            "categories": ["house"],
            "exampleSentence": "Улуг өрээл.",
            "exampleTranslation": "Большая комната."
        },
        {
            "id": "w_106",
            "wordTuvan": "Эжик",
            "wordRussian": "Дверь",
            "transcription": "[e'zhik]",
            "partOfSpeech": "noun",
            "difficulty": 2,
            "categories": ["house"],
            "exampleSentence": "Чаа эжик.",
            "exampleTranslation": "Новая дверь."
        },
        {
            "id": "w_107",
            "wordTuvan": "Терезе",
            "wordRussian": "Окно",
            "transcription": "[te'reze]",
            "partOfSpeech": "noun",
            "difficulty": 2,
            "categories": ["house"],
            "exampleSentence": "Биче терезе.",
            "exampleTranslation": "Маленькое окно."
        },
        {
            "id": "w_108",
            "wordTuvan": "Стол",
            "wordRussian": "Стол",
            "transcription": "[stol]",
            "partOfSpeech": "noun",
            "difficulty": 1,
            "categories": ["house"],
            "exampleSentence": "Улуг стол.",
            "exampleTranslation": "Большой стол."
        },
        {
            "id": "w_109",
            "wordTuvan": "Санды",
            "wordRussian": "Стул",
            "transcription": "[san'dy]",
            "partOfSpeech": "noun",
            "difficulty": 2,
            "categories": ["house"],
            "exampleSentence": "Чаа санды.",
            "exampleTranslation": "Новый стул."
        },
        {
            "id": "w_110",
            "wordTuvan": "Орун",
            "wordRussian": "Кровать / Место",
            "transcription": "[o'run]",
            "partOfSpeech": "noun",
            "difficulty": 2,
            "categories": ["house"],
            "exampleSentence": "Мээң орунум.",
            "exampleTranslation": "Моя кровать."
        },
        {
            "id": "w_111",
            "wordTuvan": "Аяк",
            "wordRussian": "Чашка / Посуда",
            "transcription": "[a'yak]",
            "partOfSpeech": "noun",
            "difficulty": 1,
            "categories": ["house"],
            "exampleSentence": "Көк аяк.",
            "exampleTranslation": "Синяя чашка."
        },
        {
            "id": "w_112",
            "wordTuvan": "Кагар",
            "wordRussian": "Шкаф",
            "transcription": "[ka'gar]",
            "partOfSpeech": "noun",
            "difficulty": 3,
            "categories": ["house"],
            "exampleSentence": "Кырган кагар.",
            "exampleTranslation": "Старый шкаф."
        },
        {
            "id": "w_113",
            "wordTuvan": "Турар",
            "wordRussian": "Вставать",
            "transcription": "[tu'rar]",
            "partOfSpeech": "verb",
            "difficulty": 2,
            "categories": ["daily_routine"],
            "exampleSentence": "Эртен мен турар мен.",
            "exampleTranslation": "Утром я встаю."
        },
        {
            "id": "w_114",
            "wordTuvan": "Чуур",
            "wordRussian": "Умываться",
            "transcription": "[chu'ur]",
            "partOfSpeech": "verb",
            "difficulty": 2,
            "categories": ["daily_routine"],
            "exampleSentence": "Мен чуур мен.",
            "exampleTranslation": "Я умываюсь."
        },
        {
            "id": "w_115",
            "wordTuvan": "Ажылдаар",
            "wordRussian": "Работать",
            "transcription": "[azhyl'da:r]",
            "partOfSpeech": "verb",
            "difficulty": 2,
            "categories": ["daily_routine"],
            "exampleSentence": "Хүн мен ажылдаап тур мен.",
            "exampleTranslation": "Днем я работаю."
        },
        {
            "id": "w_116",
            "wordTuvan": "Өөренир",
            "wordRussian": "Учиться",
            "transcription": "[ö're'nir]",
            "partOfSpeech": "verb",
            "difficulty": 2,
            "categories": ["daily_routine"],
            "exampleSentence": "Мен өөренип тур мен.",
            "exampleTranslation": "Я учусь."
        },
        {
            "id": "w_117",
            "wordTuvan": "Амыраар",
            "wordRussian": "Отдыхать",
            "transcription": "[amy'ra:r]",
            "partOfSpeech": "verb",
            "difficulty": 2,
            "categories": ["daily_routine"],
            "exampleSentence": "Кежээ мен амыраап тур мен.",
            "exampleTranslation": "Вечером я отдыхаю."
        },
        {
            "id": "w_118",
            "wordTuvan": "Узар",
            "wordRussian": "Спать",
            "transcription": "[u'zar]",
            "partOfSpeech": "verb",
            "difficulty": 2,
            "categories": ["daily_routine"],
            "exampleSentence": "Соңгу мен узап тур мен.",
            "exampleTranslation": "Ночью я сплю."
        },
        {
            "id": "w_119",
            "wordTuvan": "Бар",
            "wordRussian": "Идти",
            "transcription": "[bar]",
            "partOfSpeech": "verb",
            "difficulty": 1,
            "categories": ["daily_routine", "travel"],
            "exampleSentence": "Мен баар мен.",
            "exampleTranslation": "Я пойду."
        },
        {
            "id": "w_120",
            "wordTuvan": "Чор",
            "wordRussian": "Идти / Ехать",
            "transcription": "[chor]",
            "partOfSpeech": "verb",
            "difficulty": 2,
            "categories": ["travel", "daily_routine"],
            "exampleSentence": "Мен Кызылче чор мен.",
            "exampleTranslation": "Я еду в Кызыл."
        },
        {
            "id": "w_121",
            "wordTuvan": "Ужар",
            "wordRussian": "Лететь",
            "transcription": "[u'zhar]",
            "partOfSpeech": "verb",
            "difficulty": 3,
            "categories": ["travel"],
            "exampleSentence": "Мен чагыыр-биле ужар мен.",
            "exampleTranslation": "Я лечу на самолете."
        },
        {
            "id": "w_122",
            "wordTuvan": "Бүгү",
            "wordRussian": "Сегодня",
            "transcription": "[bü'gü]",
            "partOfSpeech": "adverb",
            "difficulty": 1,
            "categories": ["time"],
            "exampleSentence": "Бүгү мен ажылдаап тур мен.",
            "exampleTranslation": "Сегодня я работаю."
        },
        {
            "id": "w_123",
            "wordTuvan": "Эртен",
            "wordRussian": "Завтра / Утро",
            "transcription": "[er'ten]",
            "partOfSpeech": "adverb",
            "difficulty": 1,
            "categories": ["time"],
            "exampleSentence": "Эртен мен баар мен.",
            "exampleTranslation": "Завтра я пойду."
        },
        {
            "id": "w_124",
            "wordTuvan": "Дүъш",
            "wordRussian": "Вчера",
            "transcription": "[dü'sh]",
            "partOfSpeech": "adverb",
            "difficulty": 2,
            "categories": ["time"],
            "exampleSentence": "Дүъш мен бардым.",
            "exampleTranslation": "Вчера я ушел."
        },
        {
            "id": "w_125",
            "wordTuvan": "Хүн",
            "wordRussian": "День / Солнце",
            "transcription": "[hyn]",
            "partOfSpeech": "noun",
            "difficulty": 1,
            "categories": ["time", "weather"],
            "exampleSentence": "Хүн үнүп тур.",
            "exampleTranslation": "Светит солнце."
        },
        {
            "id": "w_126",
            "wordTuvan": "Кежээ",
            "wordRussian": "Вечер",
            "transcription": "[keże:'e]",
            "partOfSpeech": "noun",
            "difficulty": 1,
            "categories": ["time"],
            "exampleSentence": "Кежээ мен амыраар мен.",
            "exampleTranslation": "Вечером я отдыхаю."
        },
        {
            "id": "w_127",
            "wordTuvan": "Соңгу",
            "wordRussian": "Ночь",
            "transcription": "[soŋ'gu]",
            "partOfSpeech": "noun",
            "difficulty": 1,
            "categories": ["time"],
            "exampleSentence": "Соңгу мен узап тур мен.",
            "exampleTranslation": "Ночью я сплю."
        },
        {
            "id": "w_128",
            "wordTuvan": "Үе",
            "wordRussian": "Время",
            "transcription": "[ü'ye]",
            "partOfSpeech": "noun",
            "difficulty": 2,
            "categories": ["time"],
            "exampleSentence": "Хостуг үе.",
            "exampleTranslation": "Свободное время."
        },
        {
            "id": "w_129",
            "wordTuvan": "Поезд",
            "wordRussian": "Поезд",
            "transcription": "[po'yez]",
            "partOfSpeech": "noun",
            "difficulty": 2,
            "categories": ["travel"],
            "exampleSentence": "Мен поезд-биле чор мен.",
            "exampleTranslation": "Я еду на поезде."
        },
        {
            "id": "w_130",
            "wordTuvan": "Автобус",
            "wordRussian": "Автобус",
            "transcription": "[avto'bus]",
            "partOfSpeech": "noun",
            "difficulty": 2,
            "categories": ["travel"],
            "exampleSentence": "Автобус-биле чор.",
            "exampleTranslation": "Ехать на автобусе."
        },
        {
            "id": "w_131",
            "wordTuvan": "Чагыыр",
            "wordRussian": "Самолет",
            "transcription": "[cha'gy:r]",
            "partOfSpeech": "noun",
            "difficulty": 3,
            "categories": ["travel"],
            "exampleSentence": "Чагыыр-биле ужар.",
            "exampleTranslation": "Лететь на самолете."
        },
        {
            "id": "w_132",
            "wordTuvan": "Билет",
            "wordRussian": "Билет",
            "transcription": ["bi'let"],
            "partOfSpeech": "noun",
            "difficulty": 2,
            "categories": ["travel"],
            "exampleSentence": "Бир билет садып алыр.",
            "exampleTranslation": "Купить один билет."
        },
        {
            "id": "w_133",
            "wordTuvan": "Вокзал",
            "wordRussian": "Вокзал",
            "transcription": "[vo'kzal]",
            "partOfSpeech": "noun",
            "difficulty": 3,
            "categories": ["travel"],
            "exampleSentence": "Вокзалче баар.",
            "exampleTranslation": "Идти на вокзал."
        },
        {
            "id": "w_134",
            "wordTuvan": "Аэропорт",
            "wordRussian": "Аэропорт",
            "transcription": "[aero'port]",
            "partOfSpeech": "noun",
            "difficulty": 3,
            "categories": ["travel"],
            "exampleSentence": "Аэропортке баар мен.",
            "exampleTranslation": "Я иду в аэропорт."
        },
        {
            "id": "w_135",
            "wordTuvan": "Отулахан",
            "wordRussian": "Гостиница / Отель",
            "transcription": "[otu'lahan]",
            "partOfSpeech": "noun",
            "difficulty": 4,
            "categories": ["travel"],
            "exampleSentence": "Кайыан отулахан?",
            "exampleTranslation": "Где гостиница?"
        },
        {
            "id": "w_136",
            "wordTuvan": "Көрүшкүннер",
            "wordRussian": "Достопримечательности",
            "transcription": "[kö'rüshkünner]",
            "partOfSpeech": "noun",
            "difficulty": 4,
            "categories": ["travel"],
            "exampleSentence": "Көрүшкүннер көөр.",
            "exampleTranslation": "Смотреть достопримечательности."
        },
        {
            "id": "w_137",
            "wordTuvan": "Садып алыр",
            "wordRussian": "Купить",
            "transcription": "[sa'dyp a'lyr]",
            "partOfSpeech": "verb",
            "difficulty": 2,
            "categories": ["shopping", "travel"],
            "exampleSentence": "Мен нан садып алыр мен.",
            "exampleTranslation": "Я куплю хлеб."
        },
        {
            "id": "w_138",
            "wordTuvan": "Садыр",
            "wordRussian": "Продать",
            "transcription": "[sa'dyr]",
            "partOfSpeech": "verb",
            "difficulty": 3,
            "categories": ["shopping"],
            "exampleSentence": "Эт садыр.",
            "exampleTranslation": "Продать мясо."
        },
        {
            "id": "w_139",
            "wordTuvan": "Магазин",
            "wordRussian": "Магазин",
            "transcription": "[magazin]",
            "partOfSpeech": "noun",
            "difficulty": 2,
            "categories": ["shopping"],
            "exampleSentence": "Магазинче баар.",
            "exampleTranslation": "Идти в магазин."
        },
        {
            "id": "w_140",
            "wordTuvan": "Чыырак",
            "wordRussian": "Рынок",
            "transcription": "[chyy'rak]",
            "partOfSpeech": "noun",
            "difficulty": 3,
            "categories": ["shopping"],
            "exampleSentence": "Чыыракче баар.",
            "exampleTranslation": "Идти на рынок."
        },
        {
            "id": "w_141",
            "wordTuvan": "Үне",
            "wordRussian": "Цена",
            "transcription": "[ü'ne]",
            "partOfSpeech": "noun",
            "difficulty": 3,
            "categories": ["shopping"],
            "exampleSentence": "Үнези хире?",
            "exampleTranslation": "Сколько стоит?"
        },
        {
            "id": "w_142",
            "wordTuvan": "Акша",
            "wordRussian": "Деньги",
            "transcription": "[ak'sha]",
            "partOfSpeech": "noun",
            "difficulty": 2,
            "categories": ["shopping"],
            "exampleSentence": "Мен акша төлеп тур мен.",
            "exampleTranslation": "Я плачу деньги."
        },
        {
            "id": "w_143",
            "wordTuvan": "Доозал",
            "wordRussian": "Скидка",
            "transcription": "[do:'zal]",
            "partOfSpeech": "noun",
            "difficulty": 4,
            "categories": ["shopping"],
            "exampleSentence": "Доозал бар бе?",
            "exampleTranslation": "Есть ли скидка?"
        },
        {
            "id": "w_144",
            "wordTuvan": "Хемчээл",
            "wordRussian": "Размер",
            "transcription": "[hem'che:l]",
            "partOfSpeech": "noun",
            "difficulty": 4,
            "categories": ["shopping"],
            "exampleSentence": "Хемчээл хире?",
            "exampleTranslation": "Какой размер?"
        },
        {
            "id": "w_145",
            "wordTuvan": "Төлээр",
            "wordRussian": "Платить",
            "transcription": "[tö'le:r]",
            "partOfSpeech": "verb",
            "difficulty": 3,
            "categories": ["shopping"],
            "exampleSentence": "Акша төлээр.",
            "exampleTranslation": "Платить деньги."
        },
        {
            "id": "w_146",
            "wordTuvan": "Бээр",
            "wordRussian": "Дать",
            "transcription": "[be:r]",
            "partOfSpeech": "verb",
            "difficulty": 3,
            "categories": ["shopping"],
            "exampleSentence": "Нан бээр сил, бе.",
            "exampleTranslation": "Дайте, пожалуйста, хлеб."
        },
        {
            "id": "w_147",
            "wordTuvan": "Тып",
            "wordRussian": "Искать / Находить",
            "transcription": "[typ]",
            "partOfSpeech": "verb",
            "difficulty": 3,
            "categories": ["travel", "shopping"],
            "exampleSentence": "Мен отулыхан тып мен.",
            "exampleTranslation": "Я ищу гостиницу."
        },
        {
            "id": "w_148",
            "wordTuvan": "Көөр",
            "wordRussian": "Смотреть / Видеть",
            "transcription": "[kö:'ör]",
            "partOfSpeech": "verb",
            "difficulty": 2,
            "categories": ["travel", "hobbies"],
            "exampleSentence": "Мен көрүшкүннер көөр мен.",
            "exampleTranslation": "Я смотрю достопримечательности."
        },
        {
            "id": "w_149",
            "wordTuvan": "Баш",
            "wordRussian": "Голова",
            "transcription": "[bash]",
            "partOfSpeech": "noun",
            "difficulty": 2,
            "categories": ["health"],
            "exampleSentence": "Мээң башым аарып тур.",
            "exampleTranslation": "У меня болит голова."
        },
        {
            "id": "w_150",
            "wordTuvan": "Хол",
            "wordRussian": "Рука",
            "transcription": "[hol]",
            "partOfSpeech": "noun",
            "difficulty": 2,
            "categories": ["health"],
            "exampleSentence": "Мээң холум аарып тур.",
            "exampleTranslation": "У меня болит рука."
        },
        {
            "id": "w_151",
            "wordTuvan": "Будук",
            "wordRussian": "Нога",
            "transcription": "[bu'duk]",
            "partOfSpeech": "noun",
            "difficulty": 2,
            "categories": ["health"],
            "exampleSentence": "Мээң будук аарып тур.",
            "exampleTranslation": "У меня болит нога."
        },
        {
            "id": "w_152",
            "wordTuvan": "Карак",
            "wordRussian": "Глаз",
            "transcription": "[ka'rak]",
            "partOfSpeech": "noun",
            "difficulty": 2,
            "categories": ["health"],
            "exampleSentence": "Карактарым.",
            "exampleTranslation": "Мои глаза."
        },
        {
            "id": "w_153",
            "wordTuvan": "Кулак",
            "wordRussian": "Ухо",
            "transcription": "[ku'lak]",
            "partOfSpeech": "noun",
            "difficulty": 2,
            "categories": ["health"],
            "exampleSentence": "Кулактарым.",
            "exampleTranslation": "Мои уши."
        },
        {
            "id": "w_154",
            "wordTuvan": "Аарыг",
            "wordRussian": "Болезнь / Больной",
            "transcription": "[a:'ryg]",
            "partOfSpeech": "noun",
            "difficulty": 3,
            "categories": ["health"],
            "exampleSentence": "Мен аарыг мен.",
            "exampleTranslation": "Я болен."
        },
        {
            "id": "w_155",
            "wordTuvan": "Эмчи",
            "wordRussian": "Врач",
            "transcription": "[em'chi]",
            "partOfSpeech": "noun",
            "difficulty": 3,
            "categories": ["health"],
            "exampleSentence": "Мен эмчиге баар мен.",
            "exampleTranslation": "Я иду к врачу."
        },
        {
            "id": "w_156",
            "wordTuvan": "Эмнелге",
            "wordRussian": "Больница",
            "transcription": "[em'nelge]",
            "partOfSpeech": "noun",
            "difficulty": 3,
            "categories": ["health"],
            "exampleSentence": "Мен эмнелгеге баар мен.",
            "exampleTranslation": "Я иду в больницу."
        },
        {
            "id": "w_157",
            "wordTuvan": "Эм аптеказы",
            "wordRussian": "Аптека",
            "transcription": "[em ap'tekazy]",
            "partOfSpeech": "noun",
            "difficulty": 3,
            "categories": ["health"],
            "exampleSentence": "Мен эм аптекаже баар мен.",
            "exampleTranslation": "Я иду в аптеку."
        },
        {
            "id": "w_158",
            "wordTuvan": "Эм",
            "wordRussian": "Лекарство",
            "transcription": "[em]",
            "partOfSpeech": "noun",
            "difficulty": 3,
            "categories": ["health"],
            "exampleSentence": "Эм садып алыр.",
            "exampleTranslation": "Купить лекарство."
        },
        {
            "id": "w_159",
            "wordTuvan": "Аарып тур",
            "wordRussian": "Болит (сейчас)",
            "transcription": "[a:'ryp tur]",
            "partOfSpeech": "phrase",
            "difficulty": 3,
            "categories": ["health"],
            "exampleSentence": "Башым аарып тур.",
            "exampleTranslation": "Голова болит."
        },
        {
            "id": "w_160",
            "wordTuvan": "Чаъс",
            "wordRussian": "Дождь",
            "transcription": "[cha's]",
            "partOfSpeech": "noun",
            "difficulty": 2,
            "categories": ["weather"],
            "exampleSentence": "Чаъс чаар.",
            "exampleTranslation": "Идет дождь."
        },
        {
            "id": "w_161",
            "wordTuvan": "Кар",
            "wordRussian": "Снег",
            "transcription": "[kar]",
            "partOfSpeech": "noun",
            "difficulty": 2,
            "categories": ["weather"],
            "exampleSentence": "Кар чаар.",
            "exampleTranslation": "Идет снег."
        },
        {
            "id": "w_162",
            "wordTuvan": "Салык",
            "wordRussian": "Ветер",
            "transcription": "[sa'lyk]",
            "partOfSpeech": "noun",
            "difficulty": 2,
            "categories": ["weather"],
            "exampleSentence": "Салык үзер.",
            "exampleTranslation": "Дует ветер."
        },
        {
            "id": "w_163",
            "wordTuvan": "Изиг",
            "wordRussian": "Жарко / Горячий",
            "transcription": "[i'zig]",
            "partOfSpeech": "adjective",
            "difficulty": 2,
            "categories": ["weather"],
            "exampleSentence": "Изиг бооп тур.",
            "exampleTranslation": "Жарко."
        },
        {
            "id": "w_164",
            "wordTuvan": "Соок",
            "wordRussian": "Холодно / Холодный",
            "transcription": "[so'ok]",
            "partOfSpeech": "adjective",
            "difficulty": 2,
            "categories": ["weather"],
            "exampleSentence": "Соок бооп тур.",
            "exampleTranslation": "Холодно."
        },
        {
            "id": "w_165",
            "wordTuvan": "Час",
            "wordRussian": "Весна",
            "transcription": "[chas]",
            "partOfSpeech": "noun",
            "difficulty": 2,
            "categories": ["weather", "time"],
            "exampleSentence": "Час болгаш чай.",
            "exampleTranslation": "Весна и лето."
        },
        {
            "id": "w_166",
            "wordTuvan": "Чай",
            "wordRussian": "Лето",
            "transcription": "[chay]",
            "partOfSpeech": "noun",
            "difficulty": 2,
            "categories": ["weather", "time"],
            "exampleSentence": "Чайда изиг бооп тур.",
            "exampleTranslation": "Летом жарко."
        },
        {
            "id": "w_167",
            "wordTuvan": "Күс",
            "wordRussian": "Осень",
            "transcription": "[küs]",
            "partOfSpeech": "noun",
            "difficulty": 2,
            "categories": ["weather", "time"],
            "exampleSentence": "Күс болгаш кыш.",
            "exampleTranslation": "Осень и зима."
        },
        {
            "id": "w_168",
            "wordTuvan": "Кыш",
            "wordRussian": "Зима",
            "transcription": "[kysh]",
            "partOfSpeech": "noun",
            "difficulty": 2,
            "categories": ["weather", "time"],
            "exampleSentence": "Кышта кар чаар.",
            "exampleTranslation": "Зимой идет снег."
        },
        {
            "id": "w_169",
            "wordTuvan": "Агаар",
            "wordRussian": "Погода",
            "transcription": "[a'ga:r]",
            "partOfSpeech": "noun",
            "difficulty": 3,
            "categories": ["weather"],
            "exampleSentence": "Агаар кандыг-дыр?",
            "exampleTranslation": "Какая погода?"
        },
        {
            "id": "w_170",
            "wordTuvan": "Чаар",
            "wordRussian": "Падать (о дожде/снеге)",
            "transcription": "[cha:r]",
            "partOfSpeech": "verb",
            "difficulty": 3,
            "categories": ["weather"],
            "exampleSentence": "Эртен кар чаар.",
            "exampleTranslation": "Завтра пойдет снег."
        },
        {
            "id": "w_171",
            "wordTuvan": "Үнүп тур",
            "wordRussian": "Светить / Всходить (о солнце)",
            "transcription": "[ü'nüp tur]",
            "partOfSpeech": "phrase",
            "difficulty": 4,
            "categories": ["weather"],
            "exampleSentence": "Хүн үнүп тур.",
            "exampleTranslation": "Светит солнце."
        },
        {
            "id": "w_172",
            "wordTuvan": "Үзер",
            "wordRussian": "Дуть (о ветре)",
            "transcription": "[ü'zer]",
            "partOfSpeech": "verb",
            "difficulty": 4,
            "categories": ["weather"],
            "exampleSentence": "Салык үзер.",
            "exampleTranslation": "Будет ветер."
        },
        {
            "id": "w_173",
            "wordTuvan": "Эки",
            "wordRussian": "Хороший / Хорошо",
            "transcription": "[e'ki]",
            "partOfSpeech": "adjective",
            "difficulty": 1,
            "categories": ["basics", "weather"],
            "exampleSentence": "Агаар эки.",
            "exampleTranslation": "Погода хорошая."
        },
        {
            "id": "w_174",
            "wordTuvan": "Багай",
            "wordRussian": "Плохой / Плохо",
            "transcription": "[ba'gay]",
            "partOfSpeech": "adjective",
            "difficulty": 1,
            "categories": ["basics", "weather"],
            "exampleSentence": "Агаар багай.",
            "exampleTranslation": "Погода плохая."
        },
        {
            "id": "w_175",
            "wordTuvan": "Спорт",
            "wordRussian": "Спорт",
            "transcription": "[sport]",
            "partOfSpeech": "noun",
            "difficulty": 2,
            "categories": ["hobbies"],
            "exampleSentence": "Мен спорту өөрээр мен.",
            "exampleTranslation": "Я люблю спорт."
        },
        {
            "id": "w_176",
            "wordTuvan": "Хөгжүм",
            "wordRussian": "Музыка",
            "transcription": "[hö'zhüm]",
            "partOfSpeech": "noun",
            "difficulty": 2,
            "categories": ["hobbies"],
            "exampleSentence": "Мен хөгжүм өөрээвес мен.",
            "exampleTranslation": "Я не люблю музыку."
        },
        {
            "id": "w_177",
            "wordTuvan": "Номчулга",
            "wordRussian": "Чтение",
            "transcription": "[nom'chulga]",
            "partOfSpeech": "noun",
            "difficulty": 3,
            "categories": ["hobbies"],
            "exampleSentence": "Мен номчулганы өөрээр мен.",
            "exampleTranslation": "Я люблю чтение."
        },
        {
            "id": "w_178",
            "wordTuvan": "Оюннар",
            "wordRussian": "Игры",
            "transcription": "[oyun'nar]",
            "partOfSpeech": "noun",
            "difficulty": 2,
            "categories": ["hobbies"],
            "exampleSentence": "Оюннар ойнаар.",
            "exampleTranslation": "Играть в игры."
        },
        {
            "id": "w_179",
            "wordTuvan": "Чорук",
            "wordRussian": "Прогулка / Поход",
            "transcription": "[cho'ruk]",
            "partOfSpeech": "noun",
            "difficulty": 3,
            "categories": ["hobbies"],
            "exampleSentence": "Чорук кылыр.",
            "exampleTranslation": "Гулять."
        },
        {
            "id": "w_180",
            "wordTuvan": "Хостуг үе",
            "wordRussian": "Свободное время",
            "transcription": "[hos'tug ü'ye]",
            "partOfSpeech": "phrase",
            "difficulty": 3,
            "categories": ["hobbies"],
            "exampleSentence": "Хостуг үеңде чүү кылыр сен?",
            "exampleTranslation": "В свободное время что делаешь?"
        },
        {
            "id": "w_181",
            "wordTuvan": "Өөрээр",
            "wordRussian": "Любить / Нравиться",
            "transcription": "[ö:'re:r]",
            "partOfSpeech": "verb",
            "difficulty": 2,
            "categories": ["hobbies"],
            "exampleSentence": "Мен номчулганы өөрээр мен.",
            "exampleTranslation": "Я люблю чтение."
        },
        {
            "id": "w_182",
            "wordTuvan": "Номчуур",
            "wordRussian": "Читать",
            "transcription": "[nom'chu:r]",
            "partOfSpeech": "verb",
            "difficulty": 2,
            "categories": ["hobbies"],
            "exampleSentence": "Мен ном номчуур мен.",
            "exampleTranslation": "Я читаю книгу."
        },
        {
            "id": "w_183",
            "wordTuvan": "Сонустаар",
            "wordRussian": "Слушать",
            "transcription": "[so'nusta:r]",
            "partOfSpeech": "verb",
            "difficulty": 3,
            "categories": ["hobbies"],
            "exampleSentence": "Мен хөгжүм сонустаар мен.",
            "exampleTranslation": "Я слушаю музыку."
        },
        {
            "id": "w_184",
            "wordTuvan": "Ойнаар",
            "wordRussian": "Играть",
            "transcription": "[oy'na:r]",
            "partOfSpeech": "verb",
            "difficulty": 2,
            "categories": ["hobbies"],
            "exampleSentence": "Эртен бис оюннар ойнаар бис.",
            "exampleTranslation": "Завтра мы будем играть."
        },
        {
            "id": "w_185",
            "wordTuvan": "Кылыр",
            "wordRussian": "Делать",
            "transcription": ["ky'lyr"],
            "partOfSpeech": "verb",
            "difficulty": 2,
            "categories": ["hobbies", "daily_routine"],
            "exampleSentence": "Чүү кылыр сен?",
            "exampleTranslation": "Что ты делаешь?"
        },
        {
            "id": "w_186",
            "wordTuvan": "Ном",
            "wordRussian": "Книга",
            "transcription": "[nom]",
            "partOfSpeech": "noun",
            "difficulty": 1,
            "categories": ["hobbies"],
            "exampleSentence": "Ном номчуур.",
            "exampleTranslation": "Читать книгу."
        },
        {
            "id": "w_187",
            "wordTuvan": "Болгаш",
            "wordRussian": "И",
            "transcription": "[bol'gash]",
            "partOfSpeech": "conjunction",
            "difficulty": 1,
            "categories": ["basics"],
            "exampleSentence": "Нан болгаш эт.",
            "exampleTranslation": "Хлеб и мясо."
        },
        {
            "id": "w_188",
            "wordTuvan": "База",
            "wordRussian": "Также / И / Тоже",
            "transcription": ["ba'za"],
            "partOfSpeech": "adverb",
            "difficulty": 2,
            "categories": ["basics"],
            "exampleSentence": "Мен база ажылдаап тур мен.",
            "exampleTranslation": "Я тоже работаю."
        },
        {
            "id": "w_189",
            "wordTuvan": "Медербес",
            "wordRussian": "Не знаю",
            "transcription": "[me'derbes]",
            "partOfSpeech": "phrase",
            "difficulty": 2,
            "categories": ["basics"],
            "exampleSentence": "Мен медербес.",
            "exampleTranslation": "Я не знаю."
        },
        {
            "id": "w_190",
            "wordTuvan": "Эки болзун!",
            "wordRussian": "Поправляйся! / Будь здоров!",
            "transcription": "[e'ki bol'zun]",
            "partOfSpeech": "phrase",
            "difficulty": 3,
            "categories": ["health", "greetings"],
            "exampleSentence": "Эки болзун!",
            "exampleTranslation": "Поправляйся!"
        }
    ]
}
